AUTHORS.rst
CHANGELOG.rst
LICENSE
MANIFEST.in
README.rst
setup.py
atlas/__init__.py
atlas/admin.py
atlas/api.py
atlas/fields.py
atlas/forms.py
atlas/generator.py
atlas/models.py
atlas/parse_countries.py
atlas/urls.py
atlas/utils.py
atlas/views.py
atlas/datasets/MaxMind/GeoIPv6.dat
atlas/datasets/MaxMind/GeoLiteCity.dat
atlas/migrations/0001_initial.py
atlas/migrations/0002_auto__del_field_location_category__add_field_location_address.py
atlas/migrations/0003_auto__chg_field_location_city.py
atlas/migrations/0004_add_distance_sphere_function.py
atlas/migrations/0005_auto__add_field_country_coordinates__add_field_region_coordinates.py
atlas/migrations/__init__.py
atlas/static/js/atlas.js
atlas/static/js/example.html
atlas/templates/atlas/select_location.html
atlas/tests/__init__.py
atlas/tests/urls.py
django_atlas.egg-info/PKG-INFO
django_atlas.egg-info/SOURCES.txt
django_atlas.egg-info/dependency_links.txt
django_atlas.egg-info/not-zip-safe
django_atlas.egg-info/requires.txt
django_atlas.egg-info/top_level.txt